blogging/__init__.py
blogging/actions.py
blogging/admin.py
blogging/context_processor.py
blogging/feeds.py
blogging/managers.py
blogging/models.py
blogging/settings.py
blogging/sitemaps.py
blogging/utils.py
blogging/views.py
blogging/locale/fr_FR/LC_MESSAGES/django.mo
blogging/locale/fr_FR/LC_MESSAGES/django.po
blogging/migrations/0001_initial.py
blogging/migrations/0002_auto_20150306_1840.py
blogging/migrations/0003_auto_20150504_1809.py
blogging/migrations/0004_auto_20150504_1826.py
blogging/migrations/__init__.py
blogging/templates/admin/blogging/post/change_form.html
blogging/templates/blogging/archives.html
blogging/templates/blogging/post_detail.html
blogging/templates/blogging/post_list.html
blogging/templates/blogging/feeds/description.html
blogging/templates/blogging/feeds/title.html
blogging/templates/blogging/partials/disqus.html
blogging/templatetags/__init__.py
blogging/templatetags/blog_posts.py
blogging/templatetags/blogging_comments.py
blogging/templatetags/categories.py
blogging/urls/__init__.py
blogging/urls/base.py
blogging/urls/short.py
blogging/urls/yearmonth.py
django_blogging-1.2.3.dist-info/DESCRIPTION.rst
django_blogging-1.2.3.dist-info/METADATA
django_blogging-1.2.3.dist-info/RECORD
django_blogging-1.2.3.dist-info/WHEEL
django_blogging-1.2.3.dist-info/metadata.json
django_blogging-1.2.3.dist-info/top_level.txt
tests/__init__.py
tests/models.py
tests/settings.py
tests/tests/__init__.py
tests/tests/test_models.py
tests/tests/test_views.py
