Metadata-Version: 2.0
Name: django-blogging
Version: 1.2.3
Summary: Django blogging app. The goal is to keep it simple and configurable
Home-page: http://github.com/jibaku/blogging
Author: Fabien Schwob
Author-email: fabien@x-phuture.com
License: BSD
Platform: UNKNOWN
Classifier: Development Status :: 5 - Production/Stable
Classifier: Environment :: Web Environment
Classifier: Intended Audience :: Developers
Classifier: License :: OSI Approved :: BSD License
Classifier: Operating System :: OS Independent
Classifier: Programming Language :: Python
Classifier: Framework :: Django
